wcache-0.1.1.dist-info/DESCRIPTION.rst
wcache-0.1.1.dist-info/METADATA
wcache-0.1.1.dist-info/RECORD
wcache-0.1.1.dist-info/WHEEL
wcache-0.1.1.dist-info/entry_points.txt
wcache-0.1.1.dist-info/metadata.json
wcache-0.1.1.dist-info/top_level.txt
web_cache/__init__.py
web_cache/helper.py
web_cache/main.py
web_cache/server.py
web_cache/storage.py
web_cache/handler/__init__.py
web_cache/handler/commons.py
web_cache/handler/handle_connect.py
web_cache/handler/handle_delete.py
web_cache/handler/handle_get.py
web_cache/handler/handle_head.py
web_cache/handler/handle_options.py
web_cache/handler/handle_post.py
web_cache/handler/handle_put.py
web_cache/handler/handle_trace.py
web_cache/handler/handler.py
web_cache/handler/util.py
