Metadata-Version: 2.0
Name: wcache
Version: 0.1.1
Summary: wcache: a tool that can help you store requested resources with redis
Home-page: http://github.com/ilpan/web_cache
Author: ilpan
Author-email: pna.dev@outlook.com
License: MIT
Keywords: web_cache http python3
Platform: UNKNOWN
Classifier: Development Status :: 4 - Beta
Classifier: Programming Language :: Python :: 3 :: Only
Classifier: Environment :: Console
Classifier: Intended Audience :: Developers
Classifier: Intended Audience :: System Administrators
Classifier: License :: OSI Approved :: Apache Software License
Classifier: Topic :: Internet :: WWW/HTTP
Classifier: Topic :: Internet :: WWW/HTTP :: HTTP Servers
Classifier: Topic :: Software Development
Classifier: Topic :: System :: Networking
Classifier: Topic :: Terminals
Classifier: Topic :: Utilities
Requires-Python: >=3
Requires-Dist: redis
